spf/__init__.py
spf/spf.py
spf/core/__init__.py
spf/core/create.py
spf/core/publish.py
spf/core/render.py
spf/core/serve.py
python_spf-0.0.1.dist-info/LICENSE
python_spf-0.0.1.dist-info/METADATA
python_spf-0.0.1.dist-info/WHEEL
python_spf-0.0.1.dist-info/entry_points.txt
python_spf-0.0.1.dist-info/top_level.txt
python_spf-0.0.1.dist-info/RECORD
